mri/__init__.py
mri/info.py
mri/generators/__init__.py
mri/generators/base.py
mri/generators/cartesian.py
mri/operators/__init__.py
mri/operators/base.py
mri/operators/fourier/__init__.py
mri/operators/fourier/base.py
mri/operators/fourier/cartesian.py
mri/operators/fourier/non_cartesian.py
mri/operators/fourier/online.py
mri/operators/fourier/orc_wrapper.py
mri/operators/fourier/utils/__init__.py
mri/operators/fourier/utils/orc_coefficients.py
mri/operators/fourier/utils/processing.py
mri/operators/gradient/__init__.py
mri/operators/gradient/base.py
mri/operators/gradient/gradient.py
mri/operators/gradient/online.py
mri/operators/gradient/utils.py
mri/operators/linear/__init__.py
mri/operators/linear/dictionary.py
mri/operators/linear/utils.py
mri/operators/linear/wavelet.py
mri/operators/proximity/__init__.py
mri/operators/proximity/ordered_weighted_l1_norm.py
mri/operators/proximity/weighted.py
mri/operators/utils/__init__.py
mri/optimizers/__init__.py
mri/optimizers/base.py
mri/optimizers/forward_backward.py
mri/optimizers/primal_dual.py
mri/optimizers/utils/__init__.py
mri/optimizers/utils/cost.py
mri/optimizers/utils/reweight.py
mri/reconstructors/__init__.py
mri/reconstructors/base.py
mri/reconstructors/calibrationless.py
mri/reconstructors/self_calibrating.py
mri/reconstructors/single_channel.py
mri/reconstructors/utils/__init__.py
mri/reconstructors/utils/extract_sensitivity_maps.py
mri/scripts/__init__.py
mri/scripts/gridsearch.py
pysap_mri-0.5.0.dist-info/LICENSE
pysap_mri-0.5.0.dist-info/METADATA
pysap_mri-0.5.0.dist-info/WHEEL
pysap_mri-0.5.0.dist-info/top_level.txt
pysap_mri-0.5.0.dist-info/RECORD
