Metadata-Version: 2.1
Name: pysap-mri
Version: 0.5.0
Summary: Python Sparse data Analysis Package external MRI plugin.
Home-page: https://github.com/CEA-COSMIC/pysap-mri
Author: 
Requires-Dist: scikit-learn >=0.19.1
Requires-Dist: progressbar2 >=3.34.3
Requires-Dist: joblib >=1.0.0
Requires-Dist: scipy >=1.3.0
Requires-Dist: scikit-image >=0.17.0
Requires-Dist: mri-nufft >=0.4.0
Requires-Dist: finufft >=2.2.0
Requires-Dist: modopt >=1.7.1
